<?xml version="1.0" encoding="UTF-8"?>
<fib_object
xmlns:xsd="http://www.w3.org/2001/XMLSchema-instance"
xmlns="http://www.biokom.info/"
xsd:schemaLocation="http://www.biokom.info/fib.xsd">
<root>
	<domains>
		<dim count="2">
			<dimension number="1" direction="horizontal"/>
			<dimension number="2" direction="vertical"/>
			<vector elements="2">
				<naturalNumber max="8" />
				<naturalNumber max="8" />
			</vector>
		</dim>
		<property name="colorGrayscale" >
			<vector elements="1">
				<naturalNumberB bit="8" />
			</vector>
		</property>
	</domains>
	<main_fib_object>
		<property>
			<vector type="property.colorGrayscale">
				<value number="1">3</value>
			</vector>
			<area define_variable="1">
				<vector type="underarea">
					<value number="1">1</value>
					<value number="2">2</value>
				</vector>
				<point>
					<vector type="position">
						<variable number="1">1</variable>
						<value number="2">1</value>
					</vector>
				</point>
			</area>
		</property>
	</main_fib_object>
</root>
</fib_object>
